{"cameraMode":{"drawMode":0,"name":"Shaded","section":"Shading Mode"},"sceneLighting":true,"audioPlay":false,"sceneViewState":{"m_AlwaysRefresh":false,"showFog":true,"showSkybox":true,"showFlares":true,"showImageEffects":true,"showParticleSystems":true,"showVisualEffectGraphs":true,"m_FxEnabled":true},"in2DMode":false,"pivot":{"x":-2.381615161895752,"y":-1.4120848178863526,"z":112.22148132324219},"rotation":{"x":-0.1562574803829193,"y":-0.005344724748283625,"z":0.0008250664104707539,"w":-0.9877318739891052},"size":2.9362621307373049,"orthographic":false}